pytest_dsl/__init__.py
pytest_dsl/cli.py
pytest_dsl/conftest_adapter.py
pytest_dsl/main_adapter.py
pytest_dsl/plugin.py
pytest_dsl/core/__init__.py
pytest_dsl/core/auth_provider.py
pytest_dsl/core/auto_decorator.py
pytest_dsl/core/auto_directory.py
pytest_dsl/core/context.py
pytest_dsl/core/custom_keyword_manager.py
pytest_dsl/core/dsl_executor.py
pytest_dsl/core/dsl_executor_utils.py
pytest_dsl/core/execution_tracker.py
pytest_dsl/core/global_context.py
pytest_dsl/core/hook_manager.py
pytest_dsl/core/hookable_keyword_manager.py
pytest_dsl/core/hookspecs.py
pytest_dsl/core/http_client.py
pytest_dsl/core/http_request.py
pytest_dsl/core/keyword_loader.py
pytest_dsl/core/keyword_manager.py
pytest_dsl/core/keyword_utils.py
pytest_dsl/core/lexer.py
pytest_dsl/core/parser.py
pytest_dsl/core/parsetab.py
pytest_dsl/core/plugin_discovery.py
pytest_dsl/core/remote_server_registry.py
pytest_dsl/core/serialization_utils.py
pytest_dsl/core/utils.py
pytest_dsl/core/validator.py
pytest_dsl/core/variable_providers.py
pytest_dsl/core/variable_utils.py
pytest_dsl/core/yaml_loader.py
pytest_dsl/core/yaml_vars.py
pytest_dsl/docs/custom_keywords.md
pytest_dsl/examples/__init__.py
pytest_dsl/examples/test_assert.py
pytest_dsl/examples/test_custom_keyword.py
pytest_dsl/examples/test_http.py
pytest_dsl/examples/test_quickstart.py
pytest_dsl/examples/assert/assertion_example.auto
pytest_dsl/examples/assert/boolean_test.auto
pytest_dsl/examples/assert/expression_test.auto
pytest_dsl/examples/custom/test_advanced_keywords.auto
pytest_dsl/examples/custom/test_custom_keywords.auto
pytest_dsl/examples/custom/test_default_values.auto
pytest_dsl/examples/http/__init__.py
pytest_dsl/examples/http/builtin_auth_test.auto
pytest_dsl/examples/http/file_reference_test.auto
pytest_dsl/examples/http/http_advanced.auto
pytest_dsl/examples/http/http_example.auto
pytest_dsl/examples/http/http_length_test.auto
pytest_dsl/examples/http/http_retry_assertions.auto
pytest_dsl-0.20.0.dist-info/licenses/LICENSE
pytest_dsl-0.20.0.dist-info/METADATA
pytest_dsl-0.20.0.dist-info/WHEEL
pytest_dsl-0.20.0.dist-info/entry_points.txt
pytest_dsl-0.20.0.dist-info/top_level.txt
pytest_dsl-0.20.0.dist-info/RECORD
