Metadata-Version: 2.4
Name: pytest-dsl
Version: 0.20.0
Summary: A DSL testing framework based on pytest
Author: Chen Shuanglin
License: MIT
Project-URL: Homepage, https://github.com/felix-1991/pytest-dsl
Project-URL: Bug Tracker, https://github.com/felix-1991/pytest-dsl/issues
Classifier: Framework :: Pytest
Classifier: Programming Language :: Python :: 3
Classifier: Programming Language :: Python :: 3.9
Classifier: Programming Language :: Python :: 3.10
Classifier: Programming Language :: Python :: 3.11
Classifier: Programming Language :: Python :: 3.12
Classifier: License :: OSI Approved :: MIT License
Classifier: Operating System :: OS Independent
Requires-Python: >=3.9
License-File: LICENSE
Requires-Dist: pytest>=7.0.0
Requires-Dist: allure-pytest>=2.9.0
Requires-Dist: ply>=3.11
Requires-Dist: filelock>=3.17.0
Requires-Dist: PyYAML==6.0.2
Requires-Dist: jsonpath-ng>=1.5.0
Requires-Dist: requests>=2.28.0
Requires-Dist: lxml>=4.9.0
Requires-Dist: jsonschema>=4.17.0
Requires-Dist: pytz>=2023.3
Requires-Dist: Jinja2>=3.0.0
Dynamic: license-file
